benqprojector/__init__.py
benqprojector/__main__.py
benqprojector/_version.py
benqprojector/benqclasses.py
benqprojector/benqconnection.py
benqprojector/benqexamine.py
benqprojector/benqprojector.py
benqprojector/py.typed
benqprojector/task_helper.py
benqprojector/configs/all.json
benqprojector/configs/ht4550i.json
benqprojector/configs/minimal.json
benqprojector/configs/ms521pts537.json
benqprojector/configs/mw519.json
benqprojector/configs/th585.json
benqprojector/configs/tk800m.json
benqprojector/configs/w1100.json
benqprojector/configs/w1110.json
benqprojector/configs/w1140.json
benqprojector/configs/w4000i.json
benqprojector/configs/w4100i.json
benqprojector/configs/w6000l.json
benqprojector/configs/x3000i.json
benqprojector-0.1.9.dist-info/METADATA
benqprojector-0.1.9.dist-info/WHEEL
benqprojector-0.1.9.dist-info/licenses/LICENSE
benqprojector-0.1.9.dist-info/RECORD
