Metadata-Version: 2.4
Name: benqprojector
Version: 0.1.9
Summary: Library to control BenQ projectors.
Project-URL: Homepage, https://github.com/rrooggiieerr/benqprojector.py
Project-URL: Issues, https://github.com/rrooggiieerr/benqprojector.py/issues
Author-email: Rogier van Staveren <rogier@batoid.com>
License: Apache-2.0
License-File: LICENSE
Classifier: Development Status :: 4 - Beta
Classifier: Intended Audience :: Developers
Classifier: License :: OSI Approved :: Apache Software License
Classifier: Operating System :: MacOS :: MacOS X
Classifier: Operating System :: POSIX
Classifier: Programming Language :: Python :: 3.11
Classifier: Programming Language :: Python :: 3.12
Classifier: Topic :: Home Automation
Classifier: Topic :: Software Development :: Libraries :: Python Modules
Requires-Python: >=3.11
Requires-Dist: aiofiles>=24.1.0
Requires-Dist: pyserial-asyncio-fast>=0.14
Requires-Dist: pyserial>=3.5
